lavague/contexts/groq/__init__.py
lavague/contexts/groq/base.py
lavague_contexts_groq-0.1.0.dist-info/METADATA
lavague_contexts_groq-0.1.0.dist-info/WHEEL
lavague_contexts_groq-0.1.0.dist-info/RECORD
